ft_drift/__init__.py
ft_drift/_modidx.py
ft_drift/cli.py
ft_drift/compare_funcs.py
ft_drift/core.py
ft_drift/model.py
ft_drift/parse.py
ft_drift-0.0.13.dist-info/LICENSE
ft_drift-0.0.13.dist-info/METADATA
ft_drift-0.0.13.dist-info/WHEEL
ft_drift-0.0.13.dist-info/entry_points.txt
ft_drift-0.0.13.dist-info/top_level.txt
ft_drift-0.0.13.dist-info/RECORD
