Metadata-Version: 2.1
Name: ft-drift
Version: 0.0.13
Summary: Check for data drift with OAI data
Home-page: https://github.com/hamelsmu/ft-drift
Author: Hamel Husain
Author-email: hamel.husain@gmail.com
License: Apache Software License 2.0
Keywords: nbdev jupyter notebook python
Classifier: Development Status :: 4 - Beta
Classifier: Intended Audience :: Developers
Classifier: Natural Language :: English
Classifier: Programming Language :: Python :: 3.7
Classifier: Programming Language :: Python :: 3.8
Classifier: Programming Language :: Python :: 3.9
Classifier: Programming Language :: Python :: 3.10
Classifier: License :: OSI Approved :: Apache Software License
Requires-Python: >=3.7
License-File: LICENSE
Requires-Dist: pandas
Requires-Dist: rich
Requires-Dist: openai >=1.12.0
Requires-Dist: scikit-learn >=1.4.1
Provides-Extra: dev
